<?xml version="1.0" encoding="UTF-8"?>
<part>
	<Author>Dr. Matthias Runte, www.mattzobricks.com</Author>
	<Description>
		<en>TrixBrix Dual Gauge Curved Track R40 / Narrow Outside</en>
		<de>TrixBrix Doppelspur Kurve R40 / Schmalspur außen</de>
		<nl>TrixBrix Dubbelspoor Bocht R40 Buitenkant</nl>
	</Description>
	<ImageURL>https://www.trixbrix.eu/</ImageURL>
	<SortingKey>TrixBrix - Z72</SortingKey>

	<SnapMargin>
		<left>0.5</left>
		<right>0.7</right>
		<top>0.375</top>
		<bottom>2.625</bottom>
	</SnapMargin>

	<ConnexionList>
		<connexion>
			<type>1</type>
			<position>
				<x>-8.1875</x>
				<y>-1.375</y>
			</position>
			<angle>180</angle>
			<angleToPrev>157.5</angleToPrev>
			<angleToNext>202.5</angleToNext>
			<nextConnexionPreference>1</nextConnexionPreference>
			<electricPlug>1</electricPlug>
		</connexion>
		<connexion>
			<type>1</type>
			<position>
				<x>7.1198</x>
				<y>1.6698</y>
			</position>
			<angle>22.5</angle>
			<angleToPrev>202.5</angleToPrev>
			<angleToNext>157.5</angleToNext>
			<nextConnexionPreference>0</nextConnexionPreference>
			<electricPlug>-1</electricPlug>
		</connexion>
	</ConnexionList>

	<hull>
		<point>
			<x>0</x>
			<y>-3</y>
		</point>
		<point>
			<x>74</x>
			<y>4</y>
		</point>
		<point>
			<x>144</x>
			<y>26</y>
		</point>
		<point>
			<x>118</x>
			<y>88</y>
		</point>
		<point>
			<x>0</x>
			<y>64</y>
		</point>
	</hull>
</part>