<?xml version="1.0" encoding="UTF-8"?>
<part>
	<Author>Dr. Matthias Runte, www.mattzobricks.com</Author>
	<Description>
		<en>TrixBrix Decoupler</en>
		<de>TrixBrix Entkupplungsgleis</de>
	</Description>
	<ImageURL>https://trixbrix.eu/en_US/p/Decoupler/789</ImageURL>
	<SortingKey>TrixBrix - Y70</SortingKey>

	<SnapMargin>
		<left>1</left>
		<right>2</right>
		<top>0.5</top>
		<bottom>0.5</bottom>
	</SnapMargin>
	
	<ConnexionList>
		<connexion>
			<type>1</type>
			<position>
				<x>1.5</x>
				<y>-4</y>
			</position>
			<angle>-90</angle>
			<nextConnexionPreference>1</nextConnexionPreference>
			<electricPlug>1</electricPlug>
		</connexion>
		<connexion>
			<type>1</type>
			<position>
				<x>1.5</x>
				<y>4</y>
			</position>
			<angle>90</angle>
			<nextConnexionPreference>0</nextConnexionPreference>
			<electricPlug>-1</electricPlug>
		</connexion>
		<connexion>
			<type>trixbrix_switchmotor</type>
			<position>
				<x>-6.5</x>
				<y>-0.5</y>
			</position>
			<angle>180</angle>
		</connexion>
	</ConnexionList>
</part>